LICENSE
MANIFEST.in
README.md
requirements.txt
setup.cfg
setup.py
grad_june/__init__.py
grad_june/cuda_utils.py
grad_june/default_parameters.py
grad_june/infection.py
grad_june/model.py
grad_june/paths.py
grad_june/runner.py
grad_june/symptoms.py
grad_june/timer.py
grad_june/transmission.py
grad_june/utils.py
grad_june.egg-info/PKG-INFO
grad_june.egg-info/SOURCES.txt
grad_june.egg-info/dependency_links.txt
grad_june.egg-info/requires.txt
grad_june.egg-info/top_level.txt
grad_june/configs/benchmark.yaml
grad_june/configs/benchmark_old.yaml
grad_june/configs/default.yaml
grad_june/configs/paper.yaml
grad_june/infection_networks/__init__.py
grad_june/infection_networks/base.py
grad_june/infection_networks/leisure_network.py
grad_june/june_world_loader/__init__.py
grad_june/june_world_loader/agent_data_loader.py
grad_june/june_world_loader/care_home_loader.py
grad_june/june_world_loader/company_loader.py
grad_june/june_world_loader/graph_loader.py
grad_june/june_world_loader/household_loader.py
grad_june/june_world_loader/leisure_loader.py
grad_june/june_world_loader/network_loader.py
grad_june/june_world_loader/school_loader.py
grad_june/june_world_loader/university_loader.py
grad_june/policies/__init__.py
grad_june/policies/close_venue_policies.py
grad_june/policies/interaction_policies.py
grad_june/policies/policies.py
grad_june/policies/quarantine_policies.py
test/__init__.py
test/conftest.py
test/data/data.pkl