Metadata-Version: 2.1
Name: grad-june
Version: 0.1.8
Summary: Differentiable implementation of the JUNE model.
Home-page: https://github.com/arnauqb/GradABM-JUNE
Author: Arnau Quera-Bofarull
Author-email: arnauq@protonmail.com
License: MIT License
License-File: LICENSE
